basket/__init__.py
basket/base.py
basket/errors.py
basket_client-1.2.0.dist-info/METADATA
basket_client-1.2.0.dist-info/WHEEL
basket_client-1.2.0.dist-info/licenses/LICENSE
basket_client-1.2.0.dist-info/RECORD
